README.rst
setup.cfg
setup.py
mistpy/__init__.py
mistpy/__version__.py
mistpy/context_wrapper.py
mistpy/decorators.py
mistpy/executable_entry.py
mistpy/metadata_extractor.py
mistpy/python_execute_script.py
mistpy/tags.py
mistpy.egg-info/PKG-INFO
mistpy.egg-info/SOURCES.txt
mistpy.egg-info/dependency_links.txt
mistpy.egg-info/not-zip-safe
mistpy.egg-info/top_level.txt
tests/decorators/__init__.py
tests/decorators/args_test.py
tests/executable_entry/__init__.py
tests/executable_entry/entries_tests.py